checkmarkandcross/__init__.py
checkmarkandcross/checkmark_128.png
checkmarkandcross/checkmark_16.png
checkmarkandcross/checkmark_192.png
checkmarkandcross/checkmark_24.png
checkmarkandcross/checkmark_256.png
checkmarkandcross/checkmark_32.png
checkmarkandcross/checkmark_384.png
checkmarkandcross/checkmark_48.png
checkmarkandcross/checkmark_512.png
checkmarkandcross/checkmark_64.png
checkmarkandcross/checkmark_96.png
checkmarkandcross/cross_128.png
checkmarkandcross/cross_16.png
checkmarkandcross/cross_192.png
checkmarkandcross/cross_24.png
checkmarkandcross/cross_256.png
checkmarkandcross/cross_32.png
checkmarkandcross/cross_384.png
checkmarkandcross/cross_48.png
checkmarkandcross/cross_512.png
checkmarkandcross/cross_64.png
checkmarkandcross/cross_96.png
checkmarkandcross-0.1.2.dist-info/METADATA
checkmarkandcross-0.1.2.dist-info/WHEEL
checkmarkandcross-0.1.2.dist-info/top_level.txt
checkmarkandcross-0.1.2.dist-info/RECORD
