Metadata-Version: 2.1
Name: checkmarkandcross
Version: 0.1.2
Summary: checkmarks and crosses
Author: Eric Tröbs
Author-email: eric.troebs@tu-ilmenau.de
Classifier: Programming Language :: Python :: 3
Classifier: License :: OSI Approved :: MIT License
Classifier: Operating System :: OS Independent
Requires-Python: >=3.6
Requires-Dist: IPython
